{
  "$schema": "https://json-schema.org/draft/2020-12/schema",
  "$id": "https://odtis.org/registry/events/operator-pki-ceremony.schema.json",
  "title": "operator.pki.ceremony",
  "description": "PKI ceremony performed.",
  "allOf": [
    {
      "$ref": "envelope.schema.json"
    },
    {
      "type": "object",
      "properties": {
        "event_type": {
          "const": "operator.pki.ceremony"
        },
        "payload": {
          "type": "object",
          "additionalProperties": true
        }
      }
    }
  ]
}
